turbo_themes/__init__.py
turbo_themes/css_variables.py
turbo_themes/manager.py
turbo_themes/mapping_config.py
turbo_themes/models.py
turbo_themes/py.typed
turbo_themes/themes.py
turbo_themes/tokens.json
turbo_themes/generated/__init__.py
turbo_themes/generated/tokens.py
turbo_themes/generated/types.py
turbo_themes-0.12.31.dist-info/METADATA
turbo_themes-0.12.31.dist-info/WHEEL
turbo_themes-0.12.31.dist-info/RECORD
